mcap_data_loader/__init__.py
mcap_data_loader/basis/cfgable.py
mcap_data_loader/basis/data_loader.py
mcap_data_loader/callers/__init__.py
mcap_data_loader/callers/arrays.py
mcap_data_loader/callers/basis.py
mcap_data_loader/callers/chain.py
mcap_data_loader/callers/curry.py
mcap_data_loader/callers/dataset.py
mcap_data_loader/callers/dict_map.py
mcap_data_loader/callers/dict_tuple.py
mcap_data_loader/callers/map.py
mcap_data_loader/callers/multi.py
mcap_data_loader/callers/nodes.py
mcap_data_loader/callers/normalize.py
mcap_data_loader/callers/policy.py
mcap_data_loader/callers/reduce.py
mcap_data_loader/callers/stack.py
mcap_data_loader/callers/splitters/binary.py
mcap_data_loader/configurers/__init__.py
mcap_data_loader/configurers/basis.py
mcap_data_loader/configurers/hydra_cfger.py
mcap_data_loader/data_types/basis.py
mcap_data_loader/datasets/dataset.py
mcap_data_loader/datasets/mcap_dataset.py
mcap_data_loader/pipelines/__init__.py
mcap_data_loader/pipelines/basis.py
mcap_data_loader/pipelines/cache.py
mcap_data_loader/pipelines/drop.py
mcap_data_loader/pipelines/flatten.py
mcap_data_loader/pipelines/horizon.py
mcap_data_loader/pipelines/merge.py
mcap_data_loader/pipelines/nested_zip.py
mcap_data_loader/pipelines/normalize.py
mcap_data_loader/pipelines/pairwise.py
mcap_data_loader/pipelines/slice.py
mcap_data_loader/schemas/FloatArray.fbs
mcap_data_loader/schemas/airbot_fbs/FloatArray.py
mcap_data_loader/schemas/airbot_fbs/__init__.py
mcap_data_loader/schemas/airbot_fbs/bfbs/FloatArray.bfbs
mcap_data_loader/schemas/airbot_fbs/bfbs/__init__.py
mcap_data_loader/scripts/add_statistics.py
mcap_data_loader/serialization/flb.py
mcap_data_loader/utils/array_like.py
mcap_data_loader/utils/av_coder.py
mcap_data_loader/utils/basic.py
mcap_data_loader/utils/dict.py
mcap_data_loader/utils/extra_itertools.py
mcap_data_loader/utils/file.py
mcap_data_loader/utils/hydra_utils.py
mcap_data_loader/utils/key.py
mcap_data_loader/utils/mcap_utils.py
mcap_data_loader-0.1.0.dist-info/LICENSE
mcap_data_loader-0.1.0.dist-info/METADATA
mcap_data_loader-0.1.0.dist-info/WHEEL
mcap_data_loader-0.1.0.dist-info/top_level.txt
mcap_data_loader-0.1.0.dist-info/RECORD
