Metadata-Version: 2.1
Name: mcap-data-loader
Version: 0.1.0
Summary: MCAP Data Loader
Author-email: OpenGHz <your.email@example.com>
License: MIT
Requires-Python: >=3.9
License-File: LICENSE
Requires-Dist: pydantic
Requires-Dist: pydantic-settings
Requires-Dist: pydantic-yaml
Requires-Dist: numpy
Requires-Dist: more-itertools
Requires-Dist: toolz
Requires-Dist: cachetools
Requires-Dist: typing-extensions
Requires-Dist: flatbuffers
Requires-Dist: foxglove-schemas-flatbuffer
Requires-Dist: mcap
Requires-Dist: pymcap
Requires-Dist: av
Requires-Dist: PyTurboJPEG
Requires-Dist: natsort
Requires-Dist: array-api-compat
Requires-Dist: types-array-api
Requires-Dist: termcolor
